odoo/addons/crm_rest_api/CHANGELOG.md
odoo/addons/crm_rest_api/README.rst
odoo/addons/crm_rest_api/__init__.py
odoo/addons/crm_rest_api/__manifest__.py
odoo/addons/crm_rest_api/services/__init__.py
odoo/addons/crm_rest_api/services/crm_lead_services.py
odoo/addons/crm_rest_api/services/schemas.py
odoo14_addon_crm_rest_api-14.0.1.0.2.dist-info/METADATA
odoo14_addon_crm_rest_api-14.0.1.0.2.dist-info/WHEEL
odoo14_addon_crm_rest_api-14.0.1.0.2.dist-info/top_level.txt
odoo14_addon_crm_rest_api-14.0.1.0.2.dist-info/RECORD
