Metadata-Version: 2.1
Name: odoo14-addon-crm-rest-api
Version: 14.0.1.0.2
Summary: Expose CRM Lead on the Rest API
Home-page: UNKNOWN
Author: Coopdevs Treball SCCL
License: UNKNOWN
Platform: UNKNOWN
Classifier: Programming Language :: Python
Classifier: Framework :: Odoo
Classifier: Framework :: Odoo :: 14.0
Requires-Python: >=3.6
Requires-Dist: odoo14-addon-base-rest
Requires-Dist: odoo14-addon-base-rest-base-structure
Requires-Dist: odoo14-addon-component
Requires-Dist: odoo (<14.1dev,>=14.0a)
